filtermessages/__init__.py
filtermessages/burden.py
filtermessages/filtermessages.py
filtermessages-2025.8.18.0.dist-info/METADATA
filtermessages-2025.8.18.0.dist-info/WHEEL
filtermessages-2025.8.18.0.dist-info/entry_points.txt
filtermessages-2025.8.18.0.dist-info/top_level.txt
filtermessages-2025.8.18.0.dist-info/RECORD
