Metadata-Version: 2.4
Name: filtermessages
Version: 2025.8.18.0
Summary: Filter system logs (messages file)
Author-email: Ann T Ropea <bedhanger@gmx.de>
License-Expression: MIT
Project-URL: Homepage, https://gitlab.com/bedhanger/mwe/-/tree/master/python/filtermessages
